{
  "type_description_msg": {
    "type_description": {
      "type_name": "mycobot_interfaces/srv/SetCoords_Response",
      "fields": [
        {
          "name": "flag",
          "type": {
            "type_id": 15,
            "capacity": 0,
            "string_capacity": 0,
            "nested_type_name": ""
          },
          "default_value": ""
        }
      ]
    },
    "referenced_type_descriptions": []
  },
  "type_hashes": [
    {
      "type_name": "mycobot_interfaces/srv/SetCoords_Response",
      "hash_string": "RIHS01_9fd6cb5fe11f68cc16589bda888154271a25a768eaf18baab06fcab8b6be5dac"
    }
  ]
}